setup.py
lepassage.egg-info/PKG-INFO
lepassage.egg-info/SOURCES.txt
lepassage.egg-info/dependency_links.txt
lepassage.egg-info/top_level.txt
progress/__init__.py
progress/bar.py
progress/colors.py
progress/counter.py
progress/spinner.py